yacron/__init__.py
yacron/__main__.py
yacron/config.py
yacron/cron.py
yacron/job.py
yacron/statsd.py
yacron/version.py
yacron-0.19.0.dist-info/LICENSE
yacron-0.19.0.dist-info/METADATA
yacron-0.19.0.dist-info/WHEEL
yacron-0.19.0.dist-info/entry_points.txt
yacron-0.19.0.dist-info/top_level.txt
yacron-0.19.0.dist-info/zip-safe
yacron-0.19.0.dist-info/RECORD
