Metadata-Version: 2.1
Name: yacron
Version: 0.19.0
Summary: A modern Cron replacement that is Docker-friendly
Home-page: https://github.com/gjcarneiro/yacron
Author: Gustavo Carneiro
Author-email: gustavocarneiro@gambitresearch.com
License: MIT license
Keywords: yacron
Platform: UNKNOWN
Classifier: Development Status :: 4 - Beta
Classifier: Intended Audience :: Developers
Classifier: License :: OSI Approved :: MIT License
Classifier: Natural Language :: English
Classifier: Programming Language :: Python :: 3 :: Only
Classifier: Programming Language :: Python :: 3.7
Classifier: Programming Language :: Python :: 3.8
Classifier: Programming Language :: Python :: 3.9
Classifier: Programming Language :: Python :: 3.10
Classifier: Environment :: Console
Classifier: Topic :: Utilities
Requires-Python: >=3.7
License-File: LICENSE
Requires-Dist: aiohttp (<4,>=3.0)
Requires-Dist: aiosmtplib
Requires-Dist: crontab (==0.22.8)
Requires-Dist: jinja2
Requires-Dist: pytz
Requires-Dist: ruamel.yaml (<0.17.5)
Requires-Dist: sentry-sdk
Requires-Dist: strictyaml (>=0.7.2)
